{
  "S1": [
    "Oranienburg",
    "Lehnitz",
    "Borgsdorf",
    "Birkenwerder",
    "Hohen Neuendorf",
    "Frohnau",
    "Hermsdorf",
    "Waidmannslust",
    "Wittenau",
    "Wilhelmsruh",
    "Schönholz",
    "Wollankstraße",
    "Bornholmer Straße",
    "Gesundbrunnen",
    "Humboldthain",
    "Nordbahnhof",
    "Oranienburger Straße",
    "Friedrichstraße",
    "Brandenburger Tor",
    "Potsdamer Platz",
    "Anhalter Bahnhof",
    "Yorckstraße (Großgörschenstraße)",
    "Julius-Leber-Brücke",
    "Schöneberg",
    "Friedenau",
    "Feuerbachstraße",
    "Rathaus Steglitz",
    "Botanischer Garten",
    "Lichterfelde West",
    "Sundgauer Straße",
    "Zehlendorf",
    "Mexikoplatz",
    "Schlachtensee",
    "Nikolassee",
    "Wannsee"
  ],
  "S2": [
    "Bernau",
    "Bernau-Friedenstal",
    "Zepernick",
    "Röntgental",
    "Buch",
    "Karow",
    "Blankenburg",
    "Pankow-Heinersdorf",
    "Pankow",
    "Bornholmer Straße",
    "Gesundbrunnen",
    "Humboldthain",
    "Nordbahnhof",
    "Oranienburger Straße",
    "Friedrichstraße",
    "Brandenburger Tor",
    "Potsdamer Platz",
    "Anhalter Bahnhof",
    "Yorckstraße",
    "Südkreuz",
    "Priesterweg",
    "Attilastraße",
    "Marienfelde",
    "Buckower Chaussee",
    "Schichauweg",
    "Lichtenrade",
    "Mahlow",
    "Blankenfelde"
  ],
  "S25": [
    "Hennigsdorf",
    "Heiligensee",
    "Schulzendorf",
    "Tegel",
    "Eichborndamm",
    "Karl-Bonhoeffer-Nervenklinik",
    "Alt-Reinickendorf",
    "Schönholz",
    "Wollankstraße",
    "Bornholmer Straße",
    "Gesundbrunnen",
    "Humboldthain",
    "Nordbahnhof",
    "Oranienburger Straße",
    "Friedrichstraße",
    "Brandenburger Tor",
    "Potsdamer Platz",
    "Anhalter Bahnhof",
    "Yorckstraße",
    "Südkreuz",
    "Priesterweg",
    "Südende",
    "Lankwitz",
    "Lichterfelde Ost",
    "Osdorfer Straße",
    "Lichterfelde Süd",
    "Teltow Stadt"
  ],
  "S26": [
    "Waidmannslust",
    "Wittenau",
    "Wilhelmsruh",
    "Schönholz",
    "Wollankstraße",
    "Bornholmer Straße",
    "Gesundbrunnen",
    "Humboldthain",
    "Nordbahnhof",
    "Oranienburger Straße",
    "Friedrichstraße",
    "Brandenburger Tor",
    "Potsdamer Platz",
    "Anhalter Bahnhof",
    "Yorckstraße",
    "Südkreuz",
    "Priesterweg",
    "Südende",
    "Lankwitz",
    "Lichterfelde Ost",
    "Osdorfer Straße",
    "Lichterfelde Süd",
    "Teltow Stadt"
  ],
  "S3": [
    "Spandau",
    "Stresow",
    "Pichelsberg",
    "Olympiastadion",
    "Heerstraße",
    "Messe Süd",
    "Westkreuz",
    "Charlottenburg",
    "Savignyplatz",
    "Zoologischer Garten",
    "Tiergarten",
    "Bellevue",
    "Hauptbahnhof",
    "Friedrichstraße",
    "Hackescher Markt",
    "Alexanderplatz",
    "Jannowitzbrücke",
    "Ostbahnhof",
    "Warschauer Straße",
    "Ostkreuz",
    "Rummelsburg",
    "Betriebsbahnhof Rummelsburg",
    "Karlshorst",
    "Wuhlheide",
    "Köpenick",
    "Hirschgarten",
    "Friedrichshagen",
    "Rahnsdorf",
    "Wilhelmshagen",
    "Erkner"
  ],
  "S41": [
    "Gesundbrunnen",
    "Schönhauser Allee",
    "Prenzlauer Allee",
    "Greifswalder Straße",
    "Landsberger Allee",
    "Storkower Straße",
    "Frankfurter Allee",
    "Ostkreuz",
    "Treptower Park",
    "Sonnenallee",
    "Neukölln",
    "Hermannstraße",
    "Tempelhof",
    "Südkreuz",
    "Schöneberg",
    "Innsbrucker Platz",
    "Bundesplatz",
    "Heidelberger Platz",
    "Hohenzollerndamm",
    "Halensee",
    "Westkreuz",
    "Messe Nord/ICC",
    "Westend",
    "Jungfernheide",
    "Beusselstraße",
    "Westhafen",
    "Wedding",
    "Gesundbrunnen"
  ],
  "S45": [
    "Südkreuz",
    "Tempelhof",
    "Hermannstraße",
    "Neukölln",
    "Köllnische Heide",
    "Baumschulenweg",
    "Schöneweide",
    "Johannisthal",
    "Adlershof",
    "Altglienicke",
    "Grünbergallee",
    "Flughafen BER Terminal 5",
    "Waßmannsdorf",
    "Flughafen BER Terminal 1-2"
  ],
  "S46": [
    "Gesundbrunnen",
    "Wedding",
    "Westhafen",
    "Beusselstraße",
    "Jungfernheide",
    "Westend",
    "Messe Nord/ICC",
    "Westkreuz",
    "Halensee",
    "Hohenzollerndamm",
    "Heidelberger Platz",
    "Bundesplatz",
    "Innsbrucker Platz",
    "Schöneberg",
    "Südkreuz",
    "Tempelhof",
    "Hermannstraße",
    "Neukölln",
    "Köllnische Heide",
    "Baumschulenweg",
    "Schöneweide",
    "Johannisthal",
    "Adlershof",
    "Grünau",
    "Eichwalde",
    "Zeuthen",
    "Wildau",
    "Königs Wusterhausen"
  ],
  "S47": [
    "Hermannstraße",
    "Neukölln",
    "Köllnische Heide",
    "Baumschulenweg",
    "Schöneweide",
    "Oberspree",
    "Spindlersfeld"
  ],
  "S5": [
    "Westkreuz",
    "Charlottenburg",
    "Savignyplatz",
    "Zoologischer Garten",
    "Tiergarten",
    "Bellevue",
    "Hauptbahnhof",
    "Friedrichstraße",
    "Hackescher Markt",
    "Alexanderplatz",
    "Jannowitzbrücke",
    "Ostbahnhof",
    "Warschauer Straße",
    "Ostkreuz",
    "Nöldnerplatz",
    "Lichtenberg",
    "Friedrichsfelde Ost",
    "Biesdorf",
    "Wuhletal",
    "Kaulsdorf",
    "Mahlsdorf",
    "Birkenstein",
    "Hoppegarten",
    "Neuenhagen",
    "Fredersdorf",
    "Petershagen Nord",
    "Strausberg",
    "Hegermühle",
    "Strausberg Stadt",
    "Strausberg Nord"
  ],
  "S7": [
    "Potsdam Hauptbahnhof",
    "Babelsberg",
    "Griebnitzsee",
    "Wannsee",
    "Nikolassee",
    "Grunewald",
    "Westkreuz",
    "Charlottenburg",
    "Savignyplatz",
    "Zoologischer Garten",
    "Tiergarten",
    "Bellevue",
    "Hauptbahnhof",
    "Friedrichstraße",
    "Hackescher Markt",
    "Alexanderplatz",
    "Jannowitzbrücke",
    "Ostbahnhof",
    "Warschauer Straße",
    "Ostkreuz",
    "Nöldnerplatz",
    "Lichtenberg",
    "Friedrichsfelde Ost",
    "Springpfuhl",
    "Poelchaustraße",
    "Marzahn",
    "Raoul-Wallenberg-Straße",
    "Mehrower Allee",
    "Ahrensfelde"
  ],
  "S75": [
    "Warschauer Straße",
    "Ostkreuz",
    "Nöldnerplatz",
    "Lichtenberg",
    "Friedrichsfelde Ost",
    "Springpfuhl",
    "Gehrenseestraße",
    "Hohenschönhausen",
    "Wartenberg "
  ],
  "S8": [
    "Birkenwerder",
    "Hohen Neuendorf",
    "Bergfelde",
    "Schönfließ",
    "Mühlenbeck-Mönchmühle",
    "Blankenburg",
    "Pankow-Heinersdorf",
    "Pankow",
    "Bornholmer Straße",
    "Schönhauser Allee",
    "Prenzlauer Allee",
    "Greifswalder Straße",
    "Landsberger Allee",
    "Storkower Straße",
    "Frankfurter Allee",
    "Ostkreuz",
    "Treptower Park",
    "Plänterwald",
    "Baumschulenweg",
    "Schöneweide",
    "Johannisthal",
    "Adlershof",
    "Grünau",
    "Eichwalde",
    "Zeuthen",
    "Wildau"
  ],
  "S85": [
    "Pankow",
    "Bornholmer Straße",
    "Schönhauser Allee",
    "Prenzlauer Allee",
    "Greifswalder Straße",
    "Landsberger Allee",
    "Storkower Straße",
    "Frankfurter Allee",
    "Ostkreuz",
    "Treptower Park",
    "Plänterwald",
    "Baumschulenweg",
    "Schöneweide",
    "Johannisthal",
    "Adlershof",
    "Grünau "
  ],
  "S9": [
    "Spandau",
    "Stresow",
    "Pichelsberg",
    "Olympiastadion",
    "Heerstraße",
    "Messe Süd",
    "Westkreuz",
    "Charlottenburg",
    "Savignyplatz",
    "Zoologischer Garten",
    "Tiergarten",
    "Bellevue",
    "Hauptbahnhof",
    "Friedrichstraße",
    "Hackescher Markt",
    "Alexanderplatz",
    "Jannowitzbrücke",
    "Ostbahnhof",
    "Warschauer Straße",
    "Treptower Park",
    "Plänterwald",
    "Baumschulenweg",
    "Schöneweide",
    "Johannisthal",
    "Adlershof",
    "Altglienicke",
    "Grünbergallee",
    "Flughafen BER Terminal 5",
    "Waßmannsdorf",
    "Flughafen BER Terminal 1-2"
  ],
  "FEX": [
    "Flughafen BER Terminal 1-2",
    "Ostkreuz",
    "Gesundbrunnen",
    "Hauptbahnhof"
  ]
}
